README.rst
setup.py
sqlbatis/__init__.py
sqlbatis/db.py
sqlbatis/dbx.py
sqlbatis/log_support.py
sqlbatis/sql_id_exec.py
sqlbatis/sql_mapper.py
sqlbatis/sql_page_exec.py
sqlx_batis.egg-info/PKG-INFO
sqlx_batis.egg-info/SOURCES.txt
sqlx_batis.egg-info/dependency_links.txt
sqlx_batis.egg-info/not-zip-safe
sqlx_batis.egg-info/requires.txt
sqlx_batis.egg-info/top_level.txt