Metadata-Version: 2.1
Name: sqlx-batis
Version: 2.1.4
Summary: A thread safe sql executor for Python like MyBatis with connection pool. It helps you automatically manage database connections and transactions. It also provides ORM operations for single tables.
Home-page: https://gitee.com/summry/sqlx-batis
Author: summy
Author-email: xiazhongbiao@126.com
License: UNKNOWN
Keywords: sql,MySQL,PostgreSQL,MyBatis,python
Platform: UNKNOWN
Requires-Python: >=3.5
